kubevirt/__init__.py
kubevirt/api_client.py
kubevirt/configuration.py
kubevirt/rest.py
kubevirt/api/__init__.py
kubevirt/api/default_api.py
kubevirt/models/__init__.py
kubevirt/models/k8s_io_api_core_v1_affinity.py
kubevirt/models/k8s_io_api_core_v1_downward_api_volume_file.py
kubevirt/models/k8s_io_api_core_v1_exec_action.py
kubevirt/models/k8s_io_api_core_v1_http_get_action.py
kubevirt/models/k8s_io_api_core_v1_http_header.py
kubevirt/models/k8s_io_api_core_v1_local_object_reference.py
kubevirt/models/k8s_io_api_core_v1_node_affinity.py
kubevirt/models/k8s_io_api_core_v1_node_selector.py
kubevirt/models/k8s_io_api_core_v1_node_selector_requirement.py
kubevirt/models/k8s_io_api_core_v1_node_selector_term.py
kubevirt/models/k8s_io_api_core_v1_object_field_selector.py
kubevirt/models/k8s_io_api_core_v1_persistent_volume_claim_spec.py
kubevirt/models/k8s_io_api_core_v1_persistent_volume_claim_volume_source.py
kubevirt/models/k8s_io_api_core_v1_pod_affinity.py
kubevirt/models/k8s_io_api_core_v1_pod_affinity_term.py
kubevirt/models/k8s_io_api_core_v1_pod_anti_affinity.py
kubevirt/models/k8s_io_api_core_v1_pod_dns_config.py
kubevirt/models/k8s_io_api_core_v1_pod_dns_config_option.py
kubevirt/models/k8s_io_api_core_v1_pod_resource_claim.py
kubevirt/models/k8s_io_api_core_v1_preferred_scheduling_term.py
kubevirt/models/k8s_io_api_core_v1_resource_field_selector.py
kubevirt/models/k8s_io_api_core_v1_tcp_socket_action.py
kubevirt/models/k8s_io_api_core_v1_toleration.py
kubevirt/models/k8s_io_api_core_v1_topology_spread_constraint.py
kubevirt/models/k8s_io_api_core_v1_typed_local_object_reference.py
kubevirt/models/k8s_io_api_core_v1_typed_object_reference.py
kubevirt/models/k8s_io_api_core_v1_volume_resource_requirements.py
kubevirt/models/k8s_io_api_core_v1_weighted_pod_affinity_term.py
kubevirt/models/k8s_io_apimachinery_pkg_api_resource_quantity.py
kubevirt/models/k8s_io_apimachinery_pkg_apis_meta_v1_api_group.py
kubevirt_py-1.7.0.dist-info/METADATA
kubevirt_py-1.7.0.dist-info/WHEEL
kubevirt_py-1.7.0.dist-info/top_level.txt
kubevirt_py-1.7.0.dist-info/RECORD
