Metadata-Version: 2.4
Name: kubevirt-py
Version: 1.7.0
Summary: KubeVirt API
Home-page: https://github.com/d4rkfella/kubevirt-py
Author-email: kubevirt-dev@googlegroups.com
Keywords: Swagger,KubeVirt API
Requires-Dist: certifi>=2017.4.17
Requires-Dist: python-dateutil>=2.1
Requires-Dist: six>=1.10
Requires-Dist: urllib3>=1.23
Dynamic: author-email
Dynamic: description
Dynamic: home-page
Dynamic: keywords
Dynamic: requires-dist
Dynamic: summary
